Compiled from "Cp14_InfiniteRecursion.java"
public class Cp14_InfiniteRecursion {
  public Cp14_InfiniteRecursion();
    Code:
       0: aload_0
       1: invokespecial #1                  // Method java/lang/Object."<init>":()V
       4: return

  public java.lang.String toString();
    Code:
       0: aload_0
       1: invokedynamic #7,  0              // InvokeDynamic #0:makeConcatWithConstants:(LCp14_InfiniteRecursion;)Ljava/lang/String;
       6: areturn

  public static void main(java.lang.String[]);
    Code:
       0: new           #11                 // class Cp14_InfiniteRecursion
       3: dup
       4: invokespecial #13                 // Method "<init>":()V
       7: astore_1
       8: getstatic     #14                 // Field java/lang/System.out:Ljava/io/PrintStream;
      11: aload_1
      12: invokevirtual #20                 // Method java/io/PrintStream.println:(Ljava/lang/Object;)V
      15: return
}
